{
  "emoji_char": "🧯",
  "emoji_codepoints": [
    "U+1F9EF"
  ],
  "layers": [
    {
      "layer_index": 0,
      "merged_layer_indices": [
        48025,
        48034,
        48035,
        48041
      ],
      "glyph_names": [
        "glyph21948",
        "glyph21957",
        "glyph21958",
        "glyph21962"
      ],
      "color": {
        "r": 66,
        "g": 66,
        "b": 66
      },
      "hex": "#424242",
      "svg_file": "emoji_layer_00.svg",
      "paths_count": 4
    },
    {
      "layer_index": 1,
      "merged_layer_indices": [
        48026,
        48037
      ],
      "glyph_names": [
        "glyph21949",
        "glyph21926"
      ],
      "color": {
        "r": 219,
        "g": 52,
        "b": 39
      },
      "hex": "#db3427",
      "svg_file": "emoji_layer_01.svg",
      "paths_count": 2
    },
    {
      "layer_index": 2,
      "merged_layer_indices": [
        48027
      ],
      "glyph_names": [
        "glyph21950"
      ],
      "color": {
        "r": 186,
        "g": 38,
        "b": 38
      },
      "hex": "#ba2626",
      "svg_file": "emoji_layer_02.svg",
      "paths_count": 1
    },
    {
      "layer_index": 3,
      "merged_layer_indices": [
        48028,
        48038
      ],
      "glyph_names": [
        "glyph21951",
        "glyph21926"
      ],
      "color": {
        "r": 250,
        "g": 250,
        "b": 250
      },
      "hex": "#fafafa",
      "svg_file": "emoji_layer_03.svg",
      "paths_count": 2
    },
    {
      "layer_index": 4,
      "merged_layer_indices": [
        48029
      ],
      "glyph_names": [
        "glyph21952"
      ],
      "color": {
        "r": 0,
        "g": 0,
        "b": 0
      },
      "hex": "#000000",
      "svg_file": "emoji_layer_04.svg",
      "paths_count": 1
    },
    {
      "layer_index": 5,
      "merged_layer_indices": [
        48030
      ],
      "glyph_names": [
        "glyph21953"
      ],
      "color": {
        "r": 255,
        "g": 238,
        "b": 88
      },
      "hex": "#ffee58",
      "svg_file": "emoji_layer_05.svg",
      "paths_count": 1
    },
    {
      "layer_index": 6,
      "merged_layer_indices": [
        48031,
        48040
      ],
      "glyph_names": [
        "glyph21954",
        "glyph21961"
      ],
      "color": {
        "r": 255,
        "g": 117,
        "b": 85
      },
      "hex": "#ff7555",
      "svg_file": "emoji_layer_06.svg",
      "paths_count": 2
    },
    {
      "layer_index": 7,
      "merged_layer_indices": [
        48032,
        48042
      ],
      "glyph_names": [
        "glyph21955",
        "glyph21963"
      ],
      "color": {
        "r": 158,
        "g": 158,
        "b": 158
      },
      "hex": "#9e9e9e",
      "svg_file": "emoji_layer_07.svg",
      "paths_count": 2
    },
    {
      "layer_index": 8,
      "merged_layer_indices": [
        48033
      ],
      "glyph_names": [
        "glyph21956"
      ],
      "color": {
        "r": 97,
        "g": 97,
        "b": 97
      },
      "hex": "#616161",
      "svg_file": "emoji_layer_08.svg",
      "paths_count": 1
    },
    {
      "layer_index": 9,
      "merged_layer_indices": [
        48036
      ],
      "glyph_names": [
        "glyph21959"
      ],
      "color": {
        "r": 117,
        "g": 117,
        "b": 117
      },
      "hex": "#757575",
      "svg_file": "emoji_layer_09.svg",
      "paths_count": 1
    },
    {
      "layer_index": 10,
      "merged_layer_indices": [
        48039
      ],
      "glyph_names": [
        "glyph21960"
      ],
      "color": {
        "r": 33,
        "g": 33,
        "b": 33
      },
      "hex": "#212121",
      "svg_file": "emoji_layer_10.svg",
      "paths_count": 1
    }
  ],
  "original_layers": [
    {
      "layer_index_global": 48025,
      "layer_index_local": 0,
      "glyph_name": "glyph21948",
      "color": {
        "r": 66,
        "g": 66,
        "b": 66
      },
      "hex": "#424242",
      "matrix": [
        [
          1,
          0,
          0
        ],
        [
          0,
          1,
          0
        ],
        [
          0,
          0,
          1
        ]
      ]
    },
    {
      "layer_index_global": 48026,
      "layer_index_local": 1,
      "glyph_name": "glyph21949",
      "color": {
        "r": 219,
        "g": 52,
        "b": 39
      },
      "hex": "#db3427",
      "matrix": [
        [
          1,
          0,
          0
        ],
        [
          0,
          1,
          0
        ],
        [
          0,
          0,
          1
        ]
      ]
    },
    {
      "layer_index_global": 48027,
      "layer_index_local": 2,
      "glyph_name": "glyph21950",
      "color": {
        "r": 186,
        "g": 38,
        "b": 38
      },
      "hex": "#ba2626",
      "matrix": [
        [
          1,
          0,
          0
        ],
        [
          0,
          1,
          0
        ],
        [
          0,
          0,
          1
        ]
      ]
    },
    {
      "layer_index_global": 48028,
      "layer_index_local": 3,
      "glyph_name": "glyph21951",
      "color": {
        "r": 250,
        "g": 250,
        "b": 250
      },
      "hex": "#fafafa",
      "matrix": [
        [
          1,
          0,
          0
        ],
        [
          0,
          1,
          0
        ],
        [
          0,
          0,
          1
        ]
      ]
    },
    {
      "layer_index_global": 48029,
      "layer_index_local": 4,
      "glyph_name": "glyph21952",
      "color": {
        "r": 0,
        "g": 0,
        "b": 0
      },
      "hex": "#000000",
      "matrix": [
        [
          1,
          0,
          0
        ],
        [
          0,
          1,
          0
        ],
        [
          0,
          0,
          1
        ]
      ]
    },
    {
      "layer_index_global": 48030,
      "layer_index_local": 5,
      "glyph_name": "glyph21953",
      "color": {
        "r": 255,
        "g": 238,
        "b": 88
      },
      "hex": "#ffee58",
      "matrix": [
        [
          1,
          0,
          0
        ],
        [
          0,
          1,
          0
        ],
        [
          0,
          0,
          1
        ]
      ]
    },
    {
      "layer_index_global": 48031,
      "layer_index_local": 6,
      "glyph_name": "glyph21954",
      "color": {
        "r": 255,
        "g": 117,
        "b": 85
      },
      "hex": "#ff7555",
      "matrix": [
        [
          1,
          0,
          0
        ],
        [
          0,
          1,
          0
        ],
        [
          0,
          0,
          1
        ]
      ]
    },
    {
      "layer_index_global": 48032,
      "layer_index_local": 7,
      "glyph_name": "glyph21955",
      "color": {
        "r": 158,
        "g": 158,
        "b": 158
      },
      "hex": "#9e9e9e",
      "matrix": [
        [
          1,
          0,
          0
        ],
        [
          0,
          1,
          0
        ],
        [
          0,
          0,
          1
        ]
      ]
    },
    {
      "layer_index_global": 48033,
      "layer_index_local": 8,
      "glyph_name": "glyph21956",
      "color": {
        "r": 97,
        "g": 97,
        "b": 97
      },
      "hex": "#616161",
      "matrix": [
        [
          1,
          0,
          0
        ],
        [
          0,
          1,
          0
        ],
        [
          0,
          0,
          1
        ]
      ]
    },
    {
      "layer_index_global": 48034,
      "layer_index_local": 9,
      "glyph_name": "glyph21957",
      "color": {
        "r": 66,
        "g": 66,
        "b": 66
      },
      "hex": "#424242",
      "matrix": [
        [
          1,
          0,
          0
        ],
        [
          0,
          1,
          0
        ],
        [
          0,
          0,
          1
        ]
      ]
    },
    {
      "layer_index_global": 48035,
      "layer_index_local": 10,
      "glyph_name": "glyph21958",
      "color": {
        "r": 66,
        "g": 66,
        "b": 66
      },
      "hex": "#424242",
      "matrix": [
        [
          1,
          0,
          0
        ],
        [
          0,
          1,
          0
        ],
        [
          0,
          0,
          1
        ]
      ]
    },
    {
      "layer_index_global": 48036,
      "layer_index_local": 11,
      "glyph_name": "glyph21959",
      "color": {
        "r": 117,
        "g": 117,
        "b": 117
      },
      "hex": "#757575",
      "matrix": [
        [
          1,
          0,
          0
        ],
        [
          0,
          1,
          0
        ],
        [
          0,
          0,
          1
        ]
      ]
    },
    {
      "layer_index_global": 48037,
      "layer_index_local": 12,
      "glyph_name": "glyph21926",
      "color": {
        "r": 219,
        "g": 52,
        "b": 39
      },
      "hex": "#db3427",
      "matrix": [
        [
          0.1732635498046875,
          6.103515625e-05,
          548.8290405273438
        ],
        [
          -6.103515625e-05,
          0.1732635498046875,
          630.980712890625
        ],
        [
          0,
          0,
          1
        ]
      ]
    },
    {
      "layer_index_global": 48038,
      "layer_index_local": 13,
      "glyph_name": "glyph21926",
      "color": {
        "r": 250,
        "g": 250,
        "b": 250
      },
      "hex": "#fafafa",
      "matrix": [
        [
          0.1112060546875,
          0.0,
          587.6141052246094
        ],
        [
          0.0,
          0.1112060546875,
          651.7216033935547
        ],
        [
          0,
          0,
          1
        ]
      ]
    },
    {
      "layer_index_global": 48039,
      "layer_index_local": 14,
      "glyph_name": "glyph21960",
      "color": {
        "r": 33,
        "g": 33,
        "b": 33
      },
      "hex": "#212121",
      "matrix": [
        [
          1,
          0,
          0
        ],
        [
          0,
          1,
          0
        ],
        [
          0,
          0,
          1
        ]
      ]
    },
    {
      "layer_index_global": 48040,
      "layer_index_local": 15,
      "glyph_name": "glyph21961",
      "color": {
        "r": 255,
        "g": 117,
        "b": 85
      },
      "hex": "#ff7555",
      "matrix": [
        [
          1,
          0,
          0
        ],
        [
          0,
          1,
          0
        ],
        [
          0,
          0,
          1
        ]
      ]
    },
    {
      "layer_index_global": 48041,
      "layer_index_local": 16,
      "glyph_name": "glyph21962",
      "color": {
        "r": 66,
        "g": 66,
        "b": 66
      },
      "hex": "#424242",
      "matrix": [
        [
          1,
          0,
          0
        ],
        [
          0,
          1,
          0
        ],
        [
          0,
          0,
          1
        ]
      ]
    },
    {
      "layer_index_global": 48042,
      "layer_index_local": 17,
      "glyph_name": "glyph21963",
      "color": {
        "r": 158,
        "g": 158,
        "b": 158
      },
      "hex": "#9e9e9e",
      "matrix": [
        [
          1,
          0,
          0
        ],
        [
          0,
          1,
          0
        ],
        [
          0,
          0,
          1
        ]
      ]
    }
  ],
  "diagnostics": []
}