{
  "emoji_char": "🤨",
  "emoji_codepoints": [
    "U+1F928"
  ],
  "layers": [
    {
      "layer_index": 0,
      "merged_layer_indices": [
        32278,
        32279,
        32280,
        32281,
        32282
      ],
      "glyph_names": [
        "glyph14485",
        "glyph16967",
        "glyph16968",
        "glyph16969",
        "glyph16970"
      ],
      "color": {
        "r": 66,
        "g": 43,
        "b": 13
      },
      "hex": "#422b0d",
      "svg_file": "emoji_layer_00.svg",
      "paths_count": 5
    },
    {
      "layer_index": 1,
      "merged_layer_indices": [
        32283,
        32284
      ],
      "glyph_names": [
        "glyph14345",
        "glyph16971"
      ],
      "color": {
        "r": 137,
        "g": 96,
        "b": 36
      },
      "hex": "#896024",
      "svg_file": "emoji_layer_01.svg",
      "paths_count": 2
    }
  ],
  "original_layers": [
    {
      "layer_index_global": 32277,
      "layer_index_local": 0,
      "glyph_name": null,
      "color": {
        "r": 0,
        "g": 0,
        "b": 0
      },
      "hex": "#000000"
    },
    {
      "layer_index_global": 32278,
      "layer_index_local": 1,
      "glyph_name": "glyph14485",
      "color": {
        "r": 66,
        "g": 43,
        "b": 13
      },
      "hex": "#422b0d",
      "matrix": [
        [
          1.0,
          0.0,
          0.0
        ],
        [
          0.0,
          1.0,
          18.75
        ],
        [
          0,
          0,
          1
        ]
      ]
    },
    {
      "layer_index_global": 32279,
      "layer_index_local": 2,
      "glyph_name": "glyph16967",
      "color": {
        "r": 66,
        "g": 43,
        "b": 13
      },
      "hex": "#422b0d",
      "matrix": [
        [
          1,
          0,
          0
        ],
        [
          0,
          1,
          0
        ],
        [
          0,
          0,
          1
        ]
      ]
    },
    {
      "layer_index_global": 32280,
      "layer_index_local": 3,
      "glyph_name": "glyph16968",
      "color": {
        "r": 66,
        "g": 43,
        "b": 13
      },
      "hex": "#422b0d",
      "matrix": [
        [
          1,
          0,
          0
        ],
        [
          0,
          1,
          0
        ],
        [
          0,
          0,
          1
        ]
      ]
    },
    {
      "layer_index_global": 32281,
      "layer_index_local": 4,
      "glyph_name": "glyph16969",
      "color": {
        "r": 66,
        "g": 43,
        "b": 13
      },
      "hex": "#422b0d",
      "matrix": [
        [
          1,
          0,
          0
        ],
        [
          0,
          1,
          0
        ],
        [
          0,
          0,
          1
        ]
      ]
    },
    {
      "layer_index_global": 32282,
      "layer_index_local": 5,
      "glyph_name": "glyph16970",
      "color": {
        "r": 66,
        "g": 43,
        "b": 13
      },
      "hex": "#422b0d",
      "matrix": [
        [
          1,
          0,
          0
        ],
        [
          0,
          1,
          0
        ],
        [
          0,
          0,
          1
        ]
      ]
    },
    {
      "layer_index_global": 32283,
      "layer_index_local": 6,
      "glyph_name": "glyph14345",
      "color": {
        "r": 137,
        "g": 96,
        "b": 36
      },
      "hex": "#896024",
      "matrix": [
        [
          1.0,
          0.0,
          -9.375
        ],
        [
          0.0,
          1.0,
          -46.875
        ],
        [
          0,
          0,
          1
        ]
      ]
    },
    {
      "layer_index_global": 32284,
      "layer_index_local": 7,
      "glyph_name": "glyph16971",
      "color": {
        "r": 137,
        "g": 96,
        "b": 36
      },
      "hex": "#896024",
      "matrix": [
        [
          1,
          0,
          0
        ],
        [
          0,
          1,
          0
        ],
        [
          0,
          0,
          1
        ]
      ]
    }
  ],
  "diagnostics": [
    {
      "layer_index_global": 32277,
      "paint_repr": "<fontTools.ttLib.tables.otTables.Paint object at 0x000001591673E660>",
      "color_idx": 0,
      "hex": "#000000"
    }
  ]
}