{
  "emoji_char": "🦹",
  "emoji_codepoints": [
    "U+1F9B9"
  ],
  "layers": [
    {
      "layer_index": 0,
      "merged_layer_indices": [
        37997,
        37999,
        38001,
        38003,
        38005,
        38007,
        38009,
        38011,
        38013,
        38015,
        38017,
        38018,
        38023,
        38026,
        38027,
        38028,
        38029,
        38030,
        38031,
        38032,
        38033,
        38034,
        38037,
        38038,
        38039,
        38042,
        38044,
        38045,
        38047
      ],
      "glyph_names": [
        "glyph19896",
        "glyph19898",
        "glyph19900",
        "glyph19902",
        "glyph19898",
        "glyph19905",
        "glyph19902",
        "glyph19908",
        "glyph19910",
        "glyph19912",
        "glyph19914",
        "glyph19915",
        "glyph19919",
        "glyph19922",
        "glyph19923",
        "glyph19924",
        "glyph19925",
        "glyph19926",
        "glyph19927",
        "glyph19928",
        "glyph19929",
        "glyph19930",
        "glyph19933",
        "glyph19934",
        "glyph19935",
        "glyph19938",
        "glyph19940",
        "glyph19941",
        "glyph19943"
      ],
      "color": {
        "r": 0,
        "g": 0,
        "b": 0
      },
      "hex": "#000000",
      "svg_file": "emoji_layer_00.svg",
      "paths_count": 29
    },
    {
      "layer_index": 1,
      "merged_layer_indices": [
        37998
      ],
      "glyph_names": [
        "glyph19897"
      ],
      "color": {
        "r": 97,
        "g": 26,
        "b": 94
      },
      "hex": "#611a5e",
      "svg_file": "emoji_layer_01.svg",
      "paths_count": 1
    },
    {
      "layer_index": 2,
      "merged_layer_indices": [
        38000,
        38002,
        38004,
        38006,
        38008,
        38010,
        38012,
        38014,
        38016,
        38040,
        38041,
        38043
      ],
      "glyph_names": [
        "glyph19899",
        "glyph19901",
        "glyph19903",
        "glyph19904",
        "glyph19906",
        "glyph19907",
        "glyph19909",
        "glyph19911",
        "glyph19913",
        "glyph19936",
        "glyph19937",
        "glyph19939"
      ],
      "color": {
        "r": 14,
        "g": 43,
        "b": 82
      },
      "hex": "#0e2b52",
      "svg_file": "emoji_layer_02.svg",
      "paths_count": 12
    },
    {
      "layer_index": 3,
      "merged_layer_indices": [
        38019,
        38021
      ],
      "glyph_names": [
        "glyph19916",
        "glyph10050"
      ],
      "color": {
        "r": 201,
        "g": 201,
        "b": 201
      },
      "hex": "#c9c9c9",
      "svg_file": "emoji_layer_03.svg",
      "paths_count": 2
    },
    {
      "layer_index": 4,
      "merged_layer_indices": [
        38020,
        38022
      ],
      "glyph_names": [
        "glyph19917",
        "glyph19918"
      ],
      "color": {
        "r": 163,
        "g": 163,
        "b": 163
      },
      "hex": "#a3a3a3",
      "svg_file": "emoji_layer_04.svg",
      "paths_count": 2
    },
    {
      "layer_index": 5,
      "merged_layer_indices": [
        38024
      ],
      "glyph_names": [
        "glyph19920"
      ],
      "color": {
        "r": 189,
        "g": 189,
        "b": 189
      },
      "hex": "#bdbdbd",
      "svg_file": "emoji_layer_05.svg",
      "paths_count": 1
    },
    {
      "layer_index": 6,
      "merged_layer_indices": [
        38025
      ],
      "glyph_names": [
        "glyph19921"
      ],
      "color": {
        "r": 130,
        "g": 130,
        "b": 130
      },
      "hex": "#828282",
      "svg_file": "emoji_layer_06.svg",
      "paths_count": 1
    },
    {
      "layer_index": 7,
      "merged_layer_indices": [
        38035,
        38036
      ],
      "glyph_names": [
        "glyph19931",
        "glyph19932"
      ],
      "color": {
        "r": 179,
        "g": 179,
        "b": 179
      },
      "hex": "#b3b3b3",
      "svg_file": "emoji_layer_07.svg",
      "paths_count": 2
    },
    {
      "layer_index": 8,
      "merged_layer_indices": [
        38046,
        38048
      ],
      "glyph_names": [
        "glyph19942",
        "glyph19944"
      ],
      "color": {
        "r": 0,
        "g": 146,
        "b": 69
      },
      "hex": "#009245",
      "svg_file": "emoji_layer_08.svg",
      "paths_count": 2
    }
  ],
  "original_layers": [
    {
      "layer_index_global": 37997,
      "layer_index_local": 0,
      "glyph_name": "glyph19896",
      "color": {
        "r": 0,
        "g": 0,
        "b": 0
      },
      "hex": "#000000",
      "matrix": [
        [
          1,
          0,
          0
        ],
        [
          0,
          1,
          0
        ],
        [
          0,
          0,
          1
        ]
      ]
    },
    {
      "layer_index_global": 37998,
      "layer_index_local": 1,
      "glyph_name": "glyph19897",
      "color": {
        "r": 97,
        "g": 26,
        "b": 94
      },
      "hex": "#611a5e",
      "matrix": [
        [
          1,
          0,
          0
        ],
        [
          0,
          1,
          0
        ],
        [
          0,
          0,
          1
        ]
      ]
    },
    {
      "layer_index_global": 37999,
      "layer_index_local": 2,
      "glyph_name": "glyph19898",
      "color": {
        "r": 0,
        "g": 0,
        "b": 0
      },
      "hex": "#000000",
      "matrix": [
        [
          1,
          0,
          0
        ],
        [
          0,
          1,
          0
        ],
        [
          0,
          0,
          1
        ]
      ]
    },
    {
      "layer_index_global": 38000,
      "layer_index_local": 3,
      "glyph_name": "glyph19899",
      "color": {
        "r": 14,
        "g": 43,
        "b": 82
      },
      "hex": "#0e2b52",
      "matrix": [
        [
          1,
          0,
          0
        ],
        [
          0,
          1,
          0
        ],
        [
          0,
          0,
          1
        ]
      ]
    },
    {
      "layer_index_global": 38001,
      "layer_index_local": 4,
      "glyph_name": "glyph19900",
      "color": {
        "r": 0,
        "g": 0,
        "b": 0
      },
      "hex": "#000000",
      "matrix": [
        [
          1,
          0,
          0
        ],
        [
          0,
          1,
          0
        ],
        [
          0,
          0,
          1
        ]
      ]
    },
    {
      "layer_index_global": 38002,
      "layer_index_local": 5,
      "glyph_name": "glyph19901",
      "color": {
        "r": 14,
        "g": 43,
        "b": 82
      },
      "hex": "#0e2b52",
      "matrix": [
        [
          1,
          0,
          0
        ],
        [
          0,
          1,
          0
        ],
        [
          0,
          0,
          1
        ]
      ]
    },
    {
      "layer_index_global": 38003,
      "layer_index_local": 6,
      "glyph_name": "glyph19902",
      "color": {
        "r": 0,
        "g": 0,
        "b": 0
      },
      "hex": "#000000",
      "matrix": [
        [
          1,
          0,
          0
        ],
        [
          0,
          1,
          0
        ],
        [
          0,
          0,
          1
        ]
      ]
    },
    {
      "layer_index_global": 38004,
      "layer_index_local": 7,
      "glyph_name": "glyph19903",
      "color": {
        "r": 14,
        "g": 43,
        "b": 82
      },
      "hex": "#0e2b52",
      "matrix": [
        [
          1,
          0,
          0
        ],
        [
          0,
          1,
          0
        ],
        [
          0,
          0,
          1
        ]
      ]
    },
    {
      "layer_index_global": 38005,
      "layer_index_local": 8,
      "glyph_name": "glyph19898",
      "color": {
        "r": 0,
        "g": 0,
        "b": 0
      },
      "hex": "#000000",
      "matrix": [
        [
          -0.9994049072265625,
          0.0005035400390625,
          1272.4656982421875
        ],
        [
          0.0,
          1.0001068115234375,
          -0.06329345703125
        ],
        [
          0,
          0,
          1
        ]
      ]
    },
    {
      "layer_index_global": 38006,
      "layer_index_local": 9,
      "glyph_name": "glyph19904",
      "color": {
        "r": 14,
        "g": 43,
        "b": 82
      },
      "hex": "#0e2b52",
      "matrix": [
        [
          1,
          0,
          0
        ],
        [
          0,
          1,
          0
        ],
        [
          0,
          0,
          1
        ]
      ]
    },
    {
      "layer_index_global": 38007,
      "layer_index_local": 10,
      "glyph_name": "glyph19905",
      "color": {
        "r": 0,
        "g": 0,
        "b": 0
      },
      "hex": "#000000",
      "matrix": [
        [
          1,
          0,
          0
        ],
        [
          0,
          1,
          0
        ],
        [
          0,
          0,
          1
        ]
      ]
    },
    {
      "layer_index_global": 38008,
      "layer_index_local": 11,
      "glyph_name": "glyph19906",
      "color": {
        "r": 14,
        "g": 43,
        "b": 82
      },
      "hex": "#0e2b52",
      "matrix": [
        [
          1,
          0,
          0
        ],
        [
          0,
          1,
          0
        ],
        [
          0,
          0,
          1
        ]
      ]
    },
    {
      "layer_index_global": 38009,
      "layer_index_local": 12,
      "glyph_name": "glyph19902",
      "color": {
        "r": 0,
        "g": 0,
        "b": 0
      },
      "hex": "#000000",
      "matrix": [
        [
          -0.9994964599609375,
          0.0012054443359375,
          1272.0986938476562
        ],
        [
          0.0,
          1.0001068115234375,
          -0.0272979736328125
        ],
        [
          0,
          0,
          1
        ]
      ]
    },
    {
      "layer_index_global": 38010,
      "layer_index_local": 13,
      "glyph_name": "glyph19907",
      "color": {
        "r": 14,
        "g": 43,
        "b": 82
      },
      "hex": "#0e2b52",
      "matrix": [
        [
          1,
          0,
          0
        ],
        [
          0,
          1,
          0
        ],
        [
          0,
          0,
          1
        ]
      ]
    },
    {
      "layer_index_global": 38011,
      "layer_index_local": 14,
      "glyph_name": "glyph19908",
      "color": {
        "r": 0,
        "g": 0,
        "b": 0
      },
      "hex": "#000000",
      "matrix": [
        [
          1,
          0,
          0
        ],
        [
          0,
          1,
          0
        ],
        [
          0,
          0,
          1
        ]
      ]
    },
    {
      "layer_index_global": 38012,
      "layer_index_local": 15,
      "glyph_name": "glyph19909",
      "color": {
        "r": 14,
        "g": 43,
        "b": 82
      },
      "hex": "#0e2b52",
      "matrix": [
        [
          1,
          0,
          0
        ],
        [
          0,
          1,
          0
        ],
        [
          0,
          0,
          1
        ]
      ]
    },
    {
      "layer_index_global": 38013,
      "layer_index_local": 16,
      "glyph_name": "glyph19910",
      "color": {
        "r": 0,
        "g": 0,
        "b": 0
      },
      "hex": "#000000",
      "matrix": [
        [
          1,
          0,
          0
        ],
        [
          0,
          1,
          0
        ],
        [
          0,
          0,
          1
        ]
      ]
    },
    {
      "layer_index_global": 38014,
      "layer_index_local": 17,
      "glyph_name": "glyph19911",
      "color": {
        "r": 14,
        "g": 43,
        "b": 82
      },
      "hex": "#0e2b52",
      "matrix": [
        [
          1,
          0,
          0
        ],
        [
          0,
          1,
          0
        ],
        [
          0,
          0,
          1
        ]
      ]
    },
    {
      "layer_index_global": 38015,
      "layer_index_local": 18,
      "glyph_name": "glyph19912",
      "color": {
        "r": 0,
        "g": 0,
        "b": 0
      },
      "hex": "#000000",
      "matrix": [
        [
          1,
          0,
          0
        ],
        [
          0,
          1,
          0
        ],
        [
          0,
          0,
          1
        ]
      ]
    },
    {
      "layer_index_global": 38016,
      "layer_index_local": 19,
      "glyph_name": "glyph19913",
      "color": {
        "r": 14,
        "g": 43,
        "b": 82
      },
      "hex": "#0e2b52",
      "matrix": [
        [
          1,
          0,
          0
        ],
        [
          0,
          1,
          0
        ],
        [
          0,
          0,
          1
        ]
      ]
    },
    {
      "layer_index_global": 38017,
      "layer_index_local": 20,
      "glyph_name": "glyph19914",
      "color": {
        "r": 0,
        "g": 0,
        "b": 0
      },
      "hex": "#000000",
      "matrix": [
        [
          1,
          0,
          0
        ],
        [
          0,
          1,
          0
        ],
        [
          0,
          0,
          1
        ]
      ]
    },
    {
      "layer_index_global": 38018,
      "layer_index_local": 21,
      "glyph_name": "glyph19915",
      "color": {
        "r": 0,
        "g": 0,
        "b": 0
      },
      "hex": "#000000",
      "matrix": [
        [
          1,
          0,
          0
        ],
        [
          0,
          1,
          0
        ],
        [
          0,
          0,
          1
        ]
      ]
    },
    {
      "layer_index_global": 38019,
      "layer_index_local": 22,
      "glyph_name": "glyph19916",
      "color": {
        "r": 201,
        "g": 201,
        "b": 201
      },
      "hex": "#c9c9c9",
      "matrix": [
        [
          1,
          0,
          0
        ],
        [
          0,
          1,
          0
        ],
        [
          0,
          0,
          1
        ]
      ]
    },
    {
      "layer_index_global": 38020,
      "layer_index_local": 23,
      "glyph_name": "glyph19917",
      "color": {
        "r": 163,
        "g": 163,
        "b": 163
      },
      "hex": "#a3a3a3",
      "matrix": [
        [
          1,
          0,
          0
        ],
        [
          0,
          1,
          0
        ],
        [
          0,
          0,
          1
        ]
      ]
    },
    {
      "layer_index_global": 38021,
      "layer_index_local": 24,
      "glyph_name": "glyph10050",
      "color": {
        "r": 201,
        "g": 201,
        "b": 201
      },
      "hex": "#c9c9c9",
      "matrix": [
        [
          0.2613983154296875,
          -0.0001068115234375,
          469.89500427246094
        ],
        [
          0.0001068115234375,
          0.2613983154296875,
          686.8757019042969
        ],
        [
          0,
          0,
          1
        ]
      ]
    },
    {
      "layer_index_global": 38022,
      "layer_index_local": 25,
      "glyph_name": "glyph19918",
      "color": {
        "r": 163,
        "g": 163,
        "b": 163
      },
      "hex": "#a3a3a3",
      "matrix": [
        [
          1,
          0,
          0
        ],
        [
          0,
          1,
          0
        ],
        [
          0,
          0,
          1
        ]
      ]
    },
    {
      "layer_index_global": 38023,
      "layer_index_local": 26,
      "glyph_name": "glyph19919",
      "color": {
        "r": 0,
        "g": 0,
        "b": 0
      },
      "hex": "#000000",
      "matrix": [
        [
          1,
          0,
          0
        ],
        [
          0,
          1,
          0
        ],
        [
          0,
          0,
          1
        ]
      ]
    },
    {
      "layer_index_global": 38024,
      "layer_index_local": 27,
      "glyph_name": "glyph19920",
      "color": {
        "r": 189,
        "g": 189,
        "b": 189
      },
      "hex": "#bdbdbd",
      "matrix": [
        [
          1,
          0,
          0
        ],
        [
          0,
          1,
          0
        ],
        [
          0,
          0,
          1
        ]
      ]
    },
    {
      "layer_index_global": 38025,
      "layer_index_local": 28,
      "glyph_name": "glyph19921",
      "color": {
        "r": 130,
        "g": 130,
        "b": 130
      },
      "hex": "#828282",
      "matrix": [
        [
          1,
          0,
          0
        ],
        [
          0,
          1,
          0
        ],
        [
          0,
          0,
          1
        ]
      ]
    },
    {
      "layer_index_global": 38026,
      "layer_index_local": 29,
      "glyph_name": "glyph19922",
      "color": {
        "r": 0,
        "g": 0,
        "b": 0
      },
      "hex": "#000000",
      "matrix": [
        [
          1,
          0,
          0
        ],
        [
          0,
          1,
          0
        ],
        [
          0,
          0,
          1
        ]
      ]
    },
    {
      "layer_index_global": 38027,
      "layer_index_local": 30,
      "glyph_name": "glyph19923",
      "color": {
        "r": 0,
        "g": 0,
        "b": 0
      },
      "hex": "#000000",
      "matrix": [
        [
          0.99969482421875,
          -0.0211944580078125,
          0.0
        ],
        [
          0.024505615234375,
          0.8639068603515625,
          0.0
        ],
        [
          0,
          0,
          1
        ]
      ]
    },
    {
      "layer_index_global": 38028,
      "layer_index_local": 31,
      "glyph_name": "glyph19924",
      "color": {
        "r": 0,
        "g": 0,
        "b": 0
      },
      "hex": "#000000",
      "matrix": [
        [
          1,
          0,
          0
        ],
        [
          0,
          1,
          0
        ],
        [
          0,
          0,
          1
        ]
      ]
    },
    {
      "layer_index_global": 38029,
      "layer_index_local": 32,
      "glyph_name": "glyph19925",
      "color": {
        "r": 0,
        "g": 0,
        "b": 0
      },
      "hex": "#000000",
      "matrix": [
        [
          1,
          0,
          0
        ],
        [
          0,
          1,
          0
        ],
        [
          0,
          0,
          1
        ]
      ]
    },
    {
      "layer_index_global": 38030,
      "layer_index_local": 33,
      "glyph_name": "glyph19926",
      "color": {
        "r": 0,
        "g": 0,
        "b": 0
      },
      "hex": "#000000",
      "matrix": [
        [
          0.926300048828125,
          0.1497039794921875,
          0.0
        ],
        [
          -0.376800537109375,
          0.3679962158203125,
          0.0
        ],
        [
          0,
          0,
          1
        ]
      ]
    },
    {
      "layer_index_global": 38031,
      "layer_index_local": 34,
      "glyph_name": "glyph19927",
      "color": {
        "r": 0,
        "g": 0,
        "b": 0
      },
      "hex": "#000000",
      "matrix": [
        [
          1,
          0,
          0
        ],
        [
          0,
          1,
          0
        ],
        [
          0,
          0,
          1
        ]
      ]
    },
    {
      "layer_index_global": 38032,
      "layer_index_local": 35,
      "glyph_name": "glyph19928",
      "color": {
        "r": 0,
        "g": 0,
        "b": 0
      },
      "hex": "#000000",
      "matrix": [
        [
          1,
          0,
          0
        ],
        [
          0,
          1,
          0
        ],
        [
          0,
          0,
          1
        ]
      ]
    },
    {
      "layer_index_global": 38033,
      "layer_index_local": 36,
      "glyph_name": "glyph19929",
      "color": {
        "r": 0,
        "g": 0,
        "b": 0
      },
      "hex": "#000000",
      "matrix": [
        [
          -0.926300048828125,
          -0.1497039794921875,
          0.0
        ],
        [
          -0.376800537109375,
          0.3679962158203125,
          0.0
        ],
        [
          0,
          0,
          1
        ]
      ]
    },
    {
      "layer_index_global": 38034,
      "layer_index_local": 37,
      "glyph_name": "glyph19930",
      "color": {
        "r": 0,
        "g": 0,
        "b": 0
      },
      "hex": "#000000",
      "matrix": [
        [
          1,
          0,
          0
        ],
        [
          0,
          1,
          0
        ],
        [
          0,
          0,
          1
        ]
      ]
    },
    {
      "layer_index_global": 38035,
      "layer_index_local": 38,
      "glyph_name": "glyph19931",
      "color": {
        "r": 179,
        "g": 179,
        "b": 179
      },
      "hex": "#b3b3b3",
      "matrix": [
        [
          1,
          0,
          0
        ],
        [
          0,
          1,
          0
        ],
        [
          0,
          0,
          1
        ]
      ]
    },
    {
      "layer_index_global": 38036,
      "layer_index_local": 39,
      "glyph_name": "glyph19932",
      "color": {
        "r": 179,
        "g": 179,
        "b": 179
      },
      "hex": "#b3b3b3",
      "matrix": [
        [
          1,
          0,
          0
        ],
        [
          0,
          1,
          0
        ],
        [
          0,
          0,
          1
        ]
      ]
    },
    {
      "layer_index_global": 38037,
      "layer_index_local": 40,
      "glyph_name": "glyph19933",
      "color": {
        "r": 0,
        "g": 0,
        "b": 0
      },
      "hex": "#000000",
      "matrix": [
        [
          0.9300537109375,
          -0.06756591796875,
          0.0
        ],
        [
          0.0168609619140625,
          0.997711181640625,
          0.0
        ],
        [
          0,
          0,
          1
        ]
      ]
    },
    {
      "layer_index_global": 38038,
      "layer_index_local": 41,
      "glyph_name": "glyph19934",
      "color": {
        "r": 0,
        "g": 0,
        "b": 0
      },
      "hex": "#000000",
      "matrix": [
        [
          1,
          0,
          0
        ],
        [
          0,
          1,
          0
        ],
        [
          0,
          0,
          1
        ]
      ]
    },
    {
      "layer_index_global": 38039,
      "layer_index_local": 42,
      "glyph_name": "glyph19935",
      "color": {
        "r": 0,
        "g": 0,
        "b": 0
      },
      "hex": "#000000",
      "matrix": [
        [
          1,
          0,
          0
        ],
        [
          0,
          1,
          0
        ],
        [
          0,
          0,
          1
        ]
      ]
    },
    {
      "layer_index_global": 38040,
      "layer_index_local": 43,
      "glyph_name": "glyph19936",
      "color": {
        "r": 14,
        "g": 43,
        "b": 82
      },
      "hex": "#0e2b52",
      "matrix": [
        [
          1,
          0,
          0
        ],
        [
          0,
          1,
          0
        ],
        [
          0,
          0,
          1
        ]
      ]
    },
    {
      "layer_index_global": 38041,
      "layer_index_local": 44,
      "glyph_name": "glyph19937",
      "color": {
        "r": 14,
        "g": 43,
        "b": 82
      },
      "hex": "#0e2b52",
      "matrix": [
        [
          1,
          0,
          0
        ],
        [
          0,
          1,
          0
        ],
        [
          0,
          0,
          1
        ]
      ]
    },
    {
      "layer_index_global": 38042,
      "layer_index_local": 45,
      "glyph_name": "glyph19938",
      "color": {
        "r": 0,
        "g": 0,
        "b": 0
      },
      "hex": "#000000",
      "matrix": [
        [
          1,
          0,
          0
        ],
        [
          0,
          1,
          0
        ],
        [
          0,
          0,
          1
        ]
      ]
    },
    {
      "layer_index_global": 38043,
      "layer_index_local": 46,
      "glyph_name": "glyph19939",
      "color": {
        "r": 14,
        "g": 43,
        "b": 82
      },
      "hex": "#0e2b52",
      "matrix": [
        [
          1,
          0,
          0
        ],
        [
          0,
          1,
          0
        ],
        [
          0,
          0,
          1
        ]
      ]
    },
    {
      "layer_index_global": 38044,
      "layer_index_local": 47,
      "glyph_name": "glyph19940",
      "color": {
        "r": 0,
        "g": 0,
        "b": 0
      },
      "hex": "#000000",
      "matrix": [
        [
          1,
          0,
          0
        ],
        [
          0,
          1,
          0
        ],
        [
          0,
          0,
          1
        ]
      ]
    },
    {
      "layer_index_global": 38045,
      "layer_index_local": 48,
      "glyph_name": "glyph19941",
      "color": {
        "r": 0,
        "g": 0,
        "b": 0
      },
      "hex": "#000000",
      "matrix": [
        [
          1,
          0,
          0
        ],
        [
          0,
          1,
          0
        ],
        [
          0,
          0,
          1
        ]
      ]
    },
    {
      "layer_index_global": 38046,
      "layer_index_local": 49,
      "glyph_name": "glyph19942",
      "color": {
        "r": 0,
        "g": 146,
        "b": 69
      },
      "hex": "#009245",
      "matrix": [
        [
          1,
          0,
          0
        ],
        [
          0,
          1,
          0
        ],
        [
          0,
          0,
          1
        ]
      ]
    },
    {
      "layer_index_global": 38047,
      "layer_index_local": 50,
      "glyph_name": "glyph19943",
      "color": {
        "r": 0,
        "g": 0,
        "b": 0
      },
      "hex": "#000000",
      "matrix": [
        [
          1,
          0,
          0
        ],
        [
          0,
          1,
          0
        ],
        [
          0,
          0,
          1
        ]
      ]
    },
    {
      "layer_index_global": 38048,
      "layer_index_local": 51,
      "glyph_name": "glyph19944",
      "color": {
        "r": 0,
        "g": 146,
        "b": 69
      },
      "hex": "#009245",
      "matrix": [
        [
          1,
          0,
          0
        ],
        [
          0,
          1,
          0
        ],
        [
          0,
          0,
          1
        ]
      ]
    }
  ],
  "diagnostics": []
}