{
  "emoji_char": "🫪",
  "emoji_codepoints": [
    "U+1FAEA"
  ],
  "layers": [
    {
      "layer_index": 0,
      "merged_layer_indices": [
        50281,
        50284,
        50287
      ],
      "glyph_names": [
        "glyph23637",
        "glyph23639",
        "glyph23642"
      ],
      "color": {
        "r": 0,
        "g": 0,
        "b": 0
      },
      "hex": "#000000",
      "svg_file": "emoji_layer_00.svg",
      "paths_count": 3
    },
    {
      "layer_index": 1,
      "merged_layer_indices": [
        50282
      ],
      "glyph_names": [
        "glyph20526"
      ],
      "color": {
        "r": 235,
        "g": 143,
        "b": 0
      },
      "hex": "#eb8f00",
      "svg_file": "emoji_layer_01.svg",
      "paths_count": 1
    },
    {
      "layer_index": 2,
      "merged_layer_indices": [
        50283
      ],
      "glyph_names": [
        "glyph23638"
      ],
      "color": {
        "r": 53,
        "g": 34,
        "b": 11
      },
      "hex": "#35220b",
      "svg_file": "emoji_layer_02.svg",
      "paths_count": 1
    },
    {
      "layer_index": 3,
      "merged_layer_indices": [
        50285,
        50288
      ],
      "glyph_names": [
        "glyph23640",
        "glyph23643"
      ],
      "color": {
        "r": 66,
        "g": 43,
        "b": 13
      },
      "hex": "#422b0d",
      "svg_file": "emoji_layer_03.svg",
      "paths_count": 2
    },
    {
      "layer_index": 4,
      "merged_layer_indices": [
        50286,
        50289
      ],
      "glyph_names": [
        "glyph23641",
        "glyph23644"
      ],
      "color": {
        "r": 137,
        "g": 96,
        "b": 36
      },
      "hex": "#896024",
      "svg_file": "emoji_layer_04.svg",
      "paths_count": 2
    }
  ],
  "original_layers": [
    {
      "layer_index_global": 50281,
      "layer_index_local": 0,
      "glyph_name": "glyph23637",
      "color": {
        "r": 0,
        "g": 0,
        "b": 0
      },
      "hex": "#000000",
      "matrix": [
        [
          1,
          0,
          0
        ],
        [
          0,
          1,
          0
        ],
        [
          0,
          0,
          1
        ]
      ]
    },
    {
      "layer_index_global": 50282,
      "layer_index_local": 1,
      "glyph_name": "glyph20526",
      "color": {
        "r": 235,
        "g": 143,
        "b": 0
      },
      "hex": "#eb8f00",
      "matrix": [
        [
          1.0,
          0.0,
          3.75
        ],
        [
          0.0,
          1.0,
          -10.311996459960938
        ],
        [
          0,
          0,
          1
        ]
      ]
    },
    {
      "layer_index_global": 50283,
      "layer_index_local": 2,
      "glyph_name": "glyph23638",
      "color": {
        "r": 53,
        "g": 34,
        "b": 11
      },
      "hex": "#35220b",
      "matrix": [
        [
          1,
          0,
          0
        ],
        [
          0,
          1,
          0
        ],
        [
          0,
          0,
          1
        ]
      ]
    },
    {
      "layer_index_global": 50284,
      "layer_index_local": 3,
      "glyph_name": "glyph23639",
      "color": {
        "r": 0,
        "g": 0,
        "b": 0
      },
      "hex": "#000000",
      "matrix": [
        [
          0.86541748046875,
          0.2723388671875,
          0.0
        ],
        [
          -0.2449951171875,
          0.9622039794921875,
          0.0
        ],
        [
          0,
          0,
          1
        ]
      ]
    },
    {
      "layer_index_global": 50285,
      "layer_index_local": 4,
      "glyph_name": "glyph23640",
      "color": {
        "r": 66,
        "g": 43,
        "b": 13
      },
      "hex": "#422b0d",
      "matrix": [
        [
          1,
          0,
          0
        ],
        [
          0,
          1,
          0
        ],
        [
          0,
          0,
          1
        ]
      ]
    },
    {
      "layer_index_global": 50286,
      "layer_index_local": 5,
      "glyph_name": "glyph23641",
      "color": {
        "r": 137,
        "g": 96,
        "b": 36
      },
      "hex": "#896024",
      "matrix": [
        [
          1,
          0,
          0
        ],
        [
          0,
          1,
          0
        ],
        [
          0,
          0,
          1
        ]
      ]
    },
    {
      "layer_index_global": 50287,
      "layer_index_local": 6,
      "glyph_name": "glyph23642",
      "color": {
        "r": 0,
        "g": 0,
        "b": 0
      },
      "hex": "#000000",
      "matrix": [
        [
          -0.86541748046875,
          -0.2723388671875,
          0.0
        ],
        [
          -0.2449951171875,
          0.9622039794921875,
          0.0
        ],
        [
          0,
          0,
          1
        ]
      ]
    },
    {
      "layer_index_global": 50288,
      "layer_index_local": 7,
      "glyph_name": "glyph23643",
      "color": {
        "r": 66,
        "g": 43,
        "b": 13
      },
      "hex": "#422b0d",
      "matrix": [
        [
          1,
          0,
          0
        ],
        [
          0,
          1,
          0
        ],
        [
          0,
          0,
          1
        ]
      ]
    },
    {
      "layer_index_global": 50289,
      "layer_index_local": 8,
      "glyph_name": "glyph23644",
      "color": {
        "r": 137,
        "g": 96,
        "b": 36
      },
      "hex": "#896024",
      "matrix": [
        [
          1,
          0,
          0
        ],
        [
          0,
          1,
          0
        ],
        [
          0,
          0,
          1
        ]
      ]
    }
  ],
  "diagnostics": []
}